setup.py
bubblesort_test/__init__.py
bubblesort_test/bubblesort.py
bubblesort_test.egg-info/PKG-INFO
bubblesort_test.egg-info/SOURCES.txt
bubblesort_test.egg-info/dependency_links.txt
bubblesort_test.egg-info/top_level.txt