Metadata-Version: 2.1
Name: bubblesort-test
Version: 1.2
Summary: This is a bubblesort tool
Home-page: https://github.com/
Author: Qiyao
Author-email: qiyao.xu@eleve.isep.fr
Classifier: Programming Language :: Python :: 3
Classifier: License :: OSI Approved :: MIT License
Classifier: Operating System :: OS Independent
